mlh/__init__.py
mlh/common_utils.py
mlh/data_from_parquet.py
mlh/s3_connect.py
mlh/snowflake_connect.py
mlh/sqlite_functions.py
mlh/support.py
mlh/woe.py
mlh-0.1.3.dist-info/METADATA
mlh-0.1.3.dist-info/WHEEL
mlh-0.1.3.dist-info/top_level.txt
mlh-0.1.3.dist-info/RECORD
