Metadata-Version: 2.1
Name: mlh
Version: 0.1.3
Summary: This package provides helper utilities for machine learning tasks. One major utility is calculation of weight of evidence
Home-page: https://github.com/devsahu99/mlh
Author: Devendra Kumar Sahu
Author-email: devsahu99@gmail.com
Classifier: Programming Language :: Python :: 3
Classifier: License :: OSI Approved :: MIT License
Classifier: Operating System :: OS Independent
Requires-Dist: pandas
Requires-Dist: scipy
Requires-Dist: matplotlib
Requires-Dist: snowflake-connector-python[pandas]
Requires-Dist: s3fs
Requires-Dist: boto3
Requires-Dist: openpyxl
Requires-Dist: xlsxwriter
